zsp_dataclasses/__init__.py
zsp_dataclasses/activity_stmts.py
zsp_dataclasses/claims_refs.py
zsp_dataclasses/core_lib.py
zsp_dataclasses/decorators.py
zsp_dataclasses/shared_stmts.py
zsp_dataclasses/types.py
zsp_dataclasses/impl/__init__.py
zsp_dataclasses/impl/action_decl.py
zsp_dataclasses/impl/action_decorator_impl.py
zsp_dataclasses/impl/action_impl.py
zsp_dataclasses/impl/activity_bind_impl.py
zsp_dataclasses/impl/activity_block_meta_t.py
zsp_dataclasses/impl/activity_decl.py
zsp_dataclasses/impl/activity_decorator_impl.py
zsp_dataclasses/impl/activity_parallel_impl.py
zsp_dataclasses/impl/activity_parallel_meta_t.py
zsp_dataclasses/impl/activity_replicate_impl.py
zsp_dataclasses/impl/activity_scope_impl.py
zsp_dataclasses/impl/activity_sequence_impl.py
zsp_dataclasses/impl/activity_sequence_meta_t.py
zsp_dataclasses/impl/activity_traverse_closure.py
zsp_dataclasses/impl/backend.py
zsp_dataclasses/impl/backend_asyncio.py
zsp_dataclasses/impl/base_decorator_impl.py
zsp_dataclasses/impl/base_t.py
zsp_dataclasses/impl/bind_all_impl.py
zsp_dataclasses/impl/component_base.py
zsp_dataclasses/impl/component_decorator_impl.py
zsp_dataclasses/impl/component_impl.py
zsp_dataclasses/impl/constraint_impl.py
zsp_dataclasses/impl/context.py
zsp_dataclasses/impl/ctor.py
zsp_dataclasses/impl/ctor_scope.py
zsp_dataclasses/impl/decorator_impl_base.py
zsp_dataclasses/impl/do_impl.py
zsp_dataclasses/impl/do_impl_meta.py
zsp_dataclasses/impl/exec_decorator_impl.py
zsp_dataclasses/impl/exec_group.py
zsp_dataclasses/impl/exec_kind_e.py
zsp_dataclasses/impl/exec_type.py
zsp_dataclasses/impl/extend_action_decorator_impl.py
zsp_dataclasses/impl/extend_base_decorator_impl.py
zsp_dataclasses/impl/extend_component_decorator_impl.py
zsp_dataclasses/impl/extend_decorator_impl.py
zsp_dataclasses/impl/extend_kind_e.py
zsp_dataclasses/impl/field_claim_impl.py
zsp_dataclasses/impl/field_pool_impl.py
zsp_dataclasses/impl/field_reg_c_impl.py
zsp_dataclasses/impl/flow_obj_kind_e.py
zuspec_dataclasses-0.0.1.6746116423.dist-info/LICENSE
zuspec_dataclasses-0.0.1.6746116423.dist-info/METADATA
zuspec_dataclasses-0.0.1.6746116423.dist-info/WHEEL
zuspec_dataclasses-0.0.1.6746116423.dist-info/top_level.txt
zuspec_dataclasses-0.0.1.6746116423.dist-info/RECORD
