Metadata-Version: 2.1
Name: zuspec-dataclasses
Version: 0.0.1.6746116423
Summary: Front-end for capturing Action Relation Level models using dataclasses
Home-page: https://github.com/zuspec/zuspec-dataclasses
Author: Matthew Ballance
Author-email: matt.ballance@gmail.com
License: Apache 2.0
Keywords: SystemVerilog,Verilog,RTL
License-File: LICENSE
Requires-Dist: pyvsc-dataclasses
